{
    "manufacturer": "preisi",
    "keyboard_name": "simple_touchpad",
    "maintainer": "preisi",
    "bootloader": "rp2040",
    "diode_direction": "COL2ROW",
    "features": {
        "bootmagic": true,
        "command": false,
        "console": false,
        "extrakey": false,
        "mousekey": true,
        "nkro": true
    },
    "matrix_pins": {
		"direct": [["GP24", "GP29", "GP28"]]
    },
    "processor": "RP2040",
    "url": "",
    "usb": {
        "device_version": "1.0.0",
        "pid": "0x4919",
        "vid": "0x1209"
    },
    "layouts": {
        "LAYOUT_touchpad": {
            "layout": [
                { "matrix": [0, 0], "x": 0, "y": 0 },
                { "matrix": [0, 1], "x": 1, "y": 0 },
                { "matrix": [0, 2], "x": 2, "y": 0 }
            ]
        }
    }
}
